playscii/__init__.py
playscii/input.py
playscii/playscii.py
playscii/games/__init__.py
playscii/games/galaga.py
playscii/games/galaga_modi.py
pyplayscii-0.2.9.dist-info/LICENSE
pyplayscii-0.2.9.dist-info/METADATA
pyplayscii-0.2.9.dist-info/WHEEL
pyplayscii-0.2.9.dist-info/top_level.txt
pyplayscii-0.2.9.dist-info/RECORD
