Metadata-Version: 2.1
Name: pyplayscii
Version: 0.2.9
Summary: Object oriented ascii art python game engine
Home-page: https://github.com/k2sebeom/pyplayscii
Author: SeBeom Lee
License: UNKNOWN
Platform: UNKNOWN
Classifier: Programming Language :: Python :: 3
Classifier: Programming Language :: Python :: 3.6
Classifier: Programming Language :: Python :: 3.7
Classifier: Programming Language :: Python :: 3.8
Requires-Dist: keyboard
Requires-Dist: windows-curses
